argtyper/__init__.py
argtyper/actions.py
argtyper/base.py
argtyper/exceptions.py
argtyper/py.typed
argtyper-0.1.0.dist-info/LICENSE
argtyper-0.1.0.dist-info/WHEEL
argtyper-0.1.0.dist-info/METADATA
argtyper-0.1.0.dist-info/RECORD
