Metadata-Version: 2.1
Name: argtyper
Version: 0.1.0
Summary: Argparser on TypeHints and Decorators
Home-page: https://argtyper.readthedocs.io/
License: MIT
Author: Georg Merzdovnik
Requires-Python: >=3.9,<4.0
Classifier: License :: OSI Approved :: MIT License
Classifier: Programming Language :: Python :: 3
Classifier: Programming Language :: Python :: 3.9
Project-URL: Repository, https://github.com/gmerz/ArgTyper
